logistics_headline_extractor/__init__.py
logistics_headline_extractor/main.py
logistics_headline_extractor/prompts.py
logistics_headline_extractor-2025.12.21191245.dist-info/METADATA
logistics_headline_extractor-2025.12.21191245.dist-info/WHEEL
logistics_headline_extractor-2025.12.21191245.dist-info/top_level.txt
logistics_headline_extractor-2025.12.21191245.dist-info/RECORD
