Metadata-Version: 2.4
Name: logistics-headline-extractor
Version: 2025.12.21191245
Summary: Extracts key information from unstructured news headlines into structured domain-specific summaries for business, logistics, and transportation sectors.
Author-email: logistics-headline-extractor <hi@eugene.plus>
License: MIT
Project-URL: Homepage, https://github.com/chigwell/logistics-headline-extractor
Requires-Python: >=3.9
Requires-Dist: langchain-llm7>=0.0.0
Requires-Dist: llmatch-messages>=0.0.0
Requires-Dist: langchain-core>=0.3.0
